ayradb/__init__.py
ayradb/core/__init__.py
ayradb/core/ayradb.py
ayradb/core/query.py
ayradb/core/table.py
ayradb/core/endpoints/__init__.py
ayradb/core/endpoints/endpoints.py
ayradb/core/exceptions/__init__.py
ayradb/core/exceptions/connection.py
ayradb/core/exceptions/invalid_table.py
ayradb/core/keep_alive/__init__.py
ayradb/core/keep_alive/request.py
ayradb/core/keep_alive/response.py
ayradb/core/manage_nodes/__init__.py
ayradb/core/manage_nodes/add_node/__init__.py
ayradb/core/manage_nodes/add_node/request.py
ayradb/core/manage_nodes/add_node/response.py
ayradb/core/manage_nodes/get_servers/__init__.py
ayradb/core/manage_nodes/get_servers/request.py
ayradb/core/manage_nodes/get_servers/response.py
ayradb/core/manage_nodes/remove_node/__init__.py
ayradb/core/manage_nodes/remove_node/request.py
ayradb/core/manage_nodes/remove_node/response.py
ayradb/core/manage_record/__init__.py
ayradb/core/manage_record/escape.py
ayradb/core/manage_record/format_key.py
ayradb/core/manage_record/unescape.py
ayradb/core/manage_record/check_existence/__init__.py
ayradb/core/manage_record/check_existence/request.py
ayradb/core/manage_record/check_existence/response.py
ayradb/core/manage_record/delete/__init__.py
ayradb/core/manage_record/delete/request.py
ayradb/core/manage_record/delete/response.py
ayradb/core/manage_record/query/__init__.py
ayradb/core/manage_record/query/request.py
ayradb/core/manage_record/query/response.py
ayradb/core/manage_record/read/__init__.py
ayradb/core/manage_record/read/request.py
ayradb/core/manage_record/read/response.py
ayradb/core/manage_record/scan/__init__.py
ayradb/core/manage_record/scan/actions.py
ayradb/core/manage_record/scan/request_scan.py
ayradb/core/manage_record/scan/request_scan_init.py
ayradb/core/manage_record/scan/response_scan.py
ayradb/core/manage_record/scan/response_scan_init.py
ayradb/core/manage_record/upsert/__init__.py
ayradb/core/manage_record/upsert/request.py
ayradb/core/manage_record/upsert/response.py
ayradb-0.4.5b0.dist-info/LICENSE
ayradb-0.4.5b0.dist-info/METADATA
ayradb-0.4.5b0.dist-info/WHEEL
ayradb-0.4.5b0.dist-info/top_level.txt
ayradb-0.4.5b0.dist-info/RECORD
