Metadata-Version: 2.1
Name: ayradb
Version: 0.4.5b0
Summary: AyraDB python client
Home-page: https://www.ayradb.com
Author: CherryData srl
Author-email: info@cherry-data.com
License: Apache-2.0
Keywords: AyraDB,client,noSQL,database,connector,key-value
Platform: UNKNOWN
Requires-Python: >=3.7
License-File: LICENSE
